aibabyllmclient/__init__.py
aibabyllmclient/llmserver_call.py
aibabyllmclient/main.py
aibabyllmclient/core/__init__.py
aibabyllmclient/core/tongos_code_pb2.py
aibabyllmclient/core/tongos_core_meta_pb2.py
aibabyllmclient/core/tongos_media_llm_req_pb2.py
aibabyllmclient/core/tongos_media_llm_res_pb2.py
aibabyllmclient/core/tongos_service_pb2.py
aibabyllmclient/core/tongos_service_pb2_grpc.py
aibabyllmclient-1.5.dist-info/METADATA
aibabyllmclient-1.5.dist-info/WHEEL
aibabyllmclient-1.5.dist-info/top_level.txt
aibabyllmclient-1.5.dist-info/RECORD
