Metadata-Version: 2.1
Name: aibabyllmclient
Version: 1.5
Summary: llmserver_call
Author: zzy
Author-email: zhaichenhao1889@163.com
